usingversion/__init__.py
usingversion-0.1.1.dist-info/LICENSE
usingversion-0.1.1.dist-info/METADATA
usingversion-0.1.1.dist-info/WHEEL
usingversion-0.1.1.dist-info/RECORD
