Metadata-Version: 2.1
Name: usingversion
Version: 0.1.1
Summary: A package to make it easy for other packages to report their version.
Author: vengroff
Author-email: vengroff@gmail.com
Requires-Python: >=3.9,<4.0
Classifier: Programming Language :: Python :: 3
Classifier: Programming Language :: Python :: 3.9
Classifier: Programming Language :: Python :: 3.10
Classifier: Programming Language :: Python :: 3.11
Requires-Dist: toml (>=0.10.2,<0.11.0)
